LICENSE
MANIFEST.in
README.md
pyproject.toml
setup.cfg
cmds/mmnode-addrbal
cmds/mmnode-blocks-info
cmds/mmnode-feeview
cmds/mmnode-halving-calculator
cmds/mmnode-netrate
cmds/mmnode-peerblocks
cmds/mmnode-ticker
mmgen_node_tools/BlocksInfo.py
mmgen_node_tools/Misc.py
mmgen_node_tools/PeerBlocks.py
mmgen_node_tools/PollDisplay.py
mmgen_node_tools/Sound.py
mmgen_node_tools/Ticker.py
mmgen_node_tools/Util.py
mmgen_node_tools/__init__.py
mmgen_node_tools/main_addrbal.py
mmgen_node_tools/main_blocks_info.py
mmgen_node_tools/main_feeview.py
mmgen_node_tools/main_halving_calculator.py
mmgen_node_tools/main_netrate.py
mmgen_node_tools/main_peerblocks.py
mmgen_node_tools/main_ticker.py
mmgen_node_tools/main_txfind.py
mmgen_node_tools.egg-info/PKG-INFO
mmgen_node_tools.egg-info/SOURCES.txt
mmgen_node_tools.egg-info/dependency_links.txt
mmgen_node_tools.egg-info/requires.txt
mmgen_node_tools.egg-info/top_level.txt
mmgen_node_tools/data/keywords
mmgen_node_tools/data/ticker-cfg.yaml
mmgen_node_tools/data/ticker-portfolio.yaml
mmgen_node_tools/data/version
test/init.sh
test/cmdtest_d/base.py
test/cmdtest_d/main.py
test/cmdtest_d/misc.py
test/cmdtest_d/regtest.py
test/cmdtest_d/include/cfg.py
test/modtest_d/ut_BlocksInfo.py
test/modtest_d/ut_dep.py
test/overlay/fakemods/mmgen_node_tools/PeerBlocks.py
test/ref/ticker/ticker-btc.json
test/ref/ticker/ticker-cfg.yaml
test/ref/ticker/ticker-finance-history.json
test/ref/ticker/ticker-finance.json
test/ref/ticker/ticker-portfolio-bad.yaml
test/ref/ticker/ticker-portfolio.yaml
test/ref/ticker/ticker.json
test/test-release.d/cfg.sh