Metadata-Version: 2.4
Name: mmgen-node-tools
Version: 3.5.0
Summary: Optional online tools for the MMGen wallet suite
Home-page: https://github.com/mmgen/mmgen-node-tools
Author: The MMGen Project
Author-email: mmgen@tuta.io
License: GNU GPL v3
Project-URL: Website, https://mmgen.org
Project-URL: Bug Tracker, https://github.com/mmgen/mmgen-node-tools/issues
Keywords: file: mmgen_node_tools/data/keywords
Platform: Linux
Platform: Armbian
Platform: Raspbian
Platform: MS Windows
Platform: MacOS
Classifier: Operating System :: POSIX :: Linux
Classifier: Operating System :: Microsoft :: Windows
Classifier: Operating System :: MacOS
Classifier: Environment :: Console
Classifier: Programming Language :: Python :: 3
Classifier: Programming Language :: C
Classifier: Framework :: AsyncIO
Classifier: Framework :: aiohttp
Classifier: Topic :: Office/Business :: Financial
Classifier: Topic :: Security :: Cryptography
Classifier: Topic :: Software Development :: Libraries :: Python Modules
Classifier: Topic :: Utilities
Classifier: Intended Audience :: Developers
Classifier: Intended Audience :: End Users/Desktop
Classifier: Intended Audience :: Financial and Insurance Industry
Classifier: Intended Audience :: System Administrators
Classifier: Development Status :: 5 - Production/Stable
Requires-Python: >=3.9
License-File: LICENSE
Requires-Dist: mmgen-wallet==16.0.0
Requires-Dist: pyyaml
Requires-Dist: yahooquery
Dynamic: license-file
